LICENSE.txt
MANIFEST.in
README.rst
bootstrap.py
buildout-before-patch.cfg
buildout-idiap.cfg
buildout.cfg
setup.py
docs/Bad.png
docs/Good.png
docs/Ugly.png
docs/conf.py
docs/experiments.rst
docs/index.rst
docs/installation.rst
docs/links.rst
xfacereclib/__init__.py
xfacereclib.paper.BeFIT2012.egg-info/PKG-INFO
xfacereclib.paper.BeFIT2012.egg-info/SOURCES.txt
xfacereclib.paper.BeFIT2012.egg-info/dependency_links.txt
xfacereclib.paper.BeFIT2012.egg-info/entry_points.txt
xfacereclib.paper.BeFIT2012.egg-info/namespace_packages.txt
xfacereclib.paper.BeFIT2012.egg-info/requires.txt
xfacereclib.paper.BeFIT2012.egg-info/top_level.txt
xfacereclib/paper/__init__.py
xfacereclib/paper/BeFIT2012/__init__.py
xfacereclib/paper/BeFIT2012/configurations.py
xfacereclib/paper/BeFIT2012/evaluate.py
xfacereclib/paper/BeFIT2012/execute.py
xfacereclib/paper/BeFIT2012/tests.py