Metadata-Version: 1.1
Name: xfacereclib.paper.BeFIT2012
Version: 1.0.0
Summary: Running the face recognition experiments as given in paper: "An Open Source Framework for Standardized Comparisons of Face Recognition Algorithms".
Home-page: http://github.com/bioidiap/xfacereclib.paper.BeFIT2012
Author: Manuel Guenther
Author-email: manuel.guenther@idiap.ch
License: LICENSE.txt
Platform: UNKNOWN
Classifier: Development Status :: 4 - Beta
Classifier: Intended Audience :: Science/Research
Classifier: License :: OSI Approved :: GNU General Public License v3 (GPLv3)
Classifier: Natural Language :: English
Classifier: Programming Language :: Python :: 2.7
Classifier: Environment :: Console
Classifier: Framework :: Buildout
Classifier: Topic :: Scientific/Engineering
